{
  "id": "d-1784595701164",
  "ts": "2026-07-21T01:02:35.015Z",
  "theme": "hanuman",
  "imageUrl": "https://raw.githubusercontent.com/visw227/pocketpanchangam-legal/main/bhakti/img/1784595693405.jpg",
  "title_te": "🕉️ మంగళవారం • హనుమంతుడి అసలైన బలం ఏమిటి?",
  "title_en": "🕉️ Tuesday • What is Hanuman's True Strength?",
  "body_te": "మనమంతా హనుమంతుడిని బలం, ధైర్యం, శక్తికి ప్రతీకగా చూస్తాం కదా.\nకానీ రామాయణం ఒక గొప్ప సత్యాన్ని చెబుతోంది.\nఅదేంటంటే… ఆయన అసలైన బలం కండరాల్లో లేదు.\nఆయన భక్తిలోనే ఉంది.\n\nశ్రీరాముడి సేవలో ఉన్నప్పుడు…\n🙏 ప్రతి విజయాన్ని శ్రీరాముడి దయగానే చూశారు.\n💪 తన శక్తిని చూసి ఎప్పుడూ గర్వపడలేదు.\n❤️ ప్రతి పనినీ \"రామకార్యం\"గానే భావించారు.\n\nఅందుకే ఆయనకు అహంకారం అంటే ఏంటో తెలియదు.\nఅహంకారం తగ్గినప్పుడు…\nభయం తగ్గుతుంది.\nసందేహం తగ్గుతుంది.\nమనసు ప్రశాంతంగా, స్థిరంగా ఉంటుంది.\nఅప్పుడే మనలో ఉన్న అసలైన శక్తి బయటికి వస్తుంది.\n\nహనుమంతుడి బలం ఆయన శరీరంలో లేదు…\nఆయన మనసులో ఉంది.\nఆ మనసు పూర్తిగా శ్రీరాముడికి అంకితం అయింది. 🙏\n\nజై శ్రీరామ్ 🚩\nఓం హనుమతే నమః 🚩",
  "body_en": "We see Hanuman as a symbol of strength, courage, and power.\nBut the great truth revealed by the Ramayana is this: His true strength is not in His muscles.\nIt lies in His devotion.\n\nWhen He was in the service of Sri Rama…\n🙏 He saw every victory as the grace of Sri Rama.\n💪 He never boasted about His own strength.\n❤️ He considered every task as \"Rama Karyam\" (Lord Rama's work).\n\nThat is why there was no place for ego in Him.\nWhere ego diminishes…\nFear decreases.\nDoubt diminishes.\nThe mind becomes stable.\nThen our true inner strength comes to light.\n\nHanuman's strength is not in His body…\nIt is in His mind, which He completely dedicated to Sri Rama. 🙏\n\nJai Sri Ram 🚩\nOm Hanumate Namah 🚩"
}